[
  {
    "rank": 1,
    "author": "竟然有肉",
    "time": "2023年12月20日 17:23",
    "title": "@Lolita樱洛芙原创 姜饼王国啭 fo zan 1.20 揪一位小宝贝 店内随机裙lolita装扮超话 ​ O抽奖详情 ​",
    "url": "https://weibo.com/2252922097/Ny17sEu1E?refer_flag=1001030103_"
  },
  {
    "rank": 2,
    "author": "-鹿筱-",
    "time": "2024年06月18日 18:31",
    "title": "#星光抽屉##lolita# 樱洛芙副牌 春侣——天鹅舞曲车专+关 我和@Lolita樱洛芙原创 7.18过 300扌由随机🧵或搭配及数据下收讠平讠仑 ​",
    "url": "https://weibo.com/2520358261/OjAsI99ML?refer_flag=1001030103_"
  },
  {
    "rank": 3,
    "author": "Lolita洋装上新",
    "time": "2025年06月24日 20:00",
    "title": "#lolita上新# #lolita洋装上新#电阻：@Lolita樱洛芙原创 ​​​ 裙子：蓝息 二团Time：6.10~7.10Price：jsk=703~770 Color：图色 ​​​",
    "url": "https://weibo.com/5993650397/Py38AfUWR?refer_flag=1001030103_"
  },
  {
    "rank": 4,
    "author": "熹熹爱吃鱼x",
    "time": "01月14日 21:09",
    "title": "狼人杀.👗：@Lolita樱洛芙原创 ​",
    "url": "https://weibo.com/3741303060/Qn7jHAQCX?refer_flag=1001030103_"
  },
  {
    "rank": 5,
    "author": "追星饼饼go",
    "time": "02月11日 15:08",
    "title": "本Lo娘终于也有自己的年服了！！刷闲鱼居然刷到祈棠雪、樱洛芙如意笺这些萌款…居然才三位数！全新带吊的也有！我直接捂心脏！捡漏姿势：闲鱼搜「祈棠雪 捡漏」或者「樱洛芙 如意笺」等等，记得按“最新发布”刷，好价真的靠手速！！已经看到好几个姐妹晒单了，我也冲了一件樱洛芙…今年过年就穿它了！姐妹们快去看看，说不定还有！！Lolita超话#lo娘年服##祈棠雪##樱洛芙如意笺##00后的年货闲鱼买# 闲鱼超划算！ 收起d",
    "url": "https://weibo.com/9073678644/QrkUWBbB2?refer_flag=1001030103_"
  }
]
